fast_ctypes_screenshots/README.md
fast_ctypes_screenshots/__init__.py
fast_ctypes_screenshots/requirements.txt
fast_ctypes_screenshots/thirdparty.json
fast_ctypes_screenshots-0.10.dist-info/LICENSE.rst
fast_ctypes_screenshots-0.10.dist-info/METADATA
fast_ctypes_screenshots-0.10.dist-info/WHEEL
fast_ctypes_screenshots-0.10.dist-info/top_level.txt
fast_ctypes_screenshots-0.10.dist-info/RECORD
