Metadata-Version: 2.1
Name: fast-ctypes-screenshots
Version: 0.10
Summary: Screenshots in record time - up to 2.5x faster than MSS (Multiple Screen Shots)
Home-page: https://github.com/hansalemaos/fast_ctypes_screenshots
Author: Johannes Fischer
Author-email: aulasparticularesdealemaosp@gmail.com
License: MIT
Keywords: screenshots,mss,fast,win32
Classifier: Development Status :: 4 - Beta
Classifier: Programming Language :: Python :: 3 :: Only
Classifier: Programming Language :: Python :: 3.10
Classifier: Topic :: Software Development :: Libraries :: Python Modules
Classifier: Topic :: Utilities
License-File: LICENSE.rst
Requires-Dist: getmonitorresolution
Requires-Dist: numpy
